decimaljs/__init__.py
decimaljs/decimal.js
decimaljs/decimaljs.py
decimaljs-1.0.4.dist-info/LICENSE
decimaljs-1.0.4.dist-info/METADATA
decimaljs-1.0.4.dist-info/WHEEL
decimaljs-1.0.4.dist-info/top_level.txt
decimaljs-1.0.4.dist-info/RECORD
