Metadata-Version: 2.1
Name: decimaljs
Version: 1.0.4
Summary: An arbitrary-precision Decimal type for JavaScript to Python
Home-page: https://github.com/kirankotari/decimaljs
Author: Kiran Kumar Kotari
Author-email: kirankotari@live.com
License: UNKNOWN
Keywords: decimal.js decimal decimaljs
Platform: UNKNOWN
Classifier: Development Status :: 5 - Production/Stable
Classifier: Intended Audience :: Developers
Classifier: Topic :: Software Development :: Build Tools
Classifier: License :: OSI Approved :: MIT License
Classifier: Programming Language :: Python :: 2.7
Classifier: Programming Language :: Python :: 3.5
Classifier: Programming Language :: Python :: 3.6
Classifier: Programming Language :: Python :: 3.7
Requires-Dist: js2py (>=0.70)
